i_rly_like_lemons/__init__.py
i_rly_like_lemons/amplifiers.txt
i_rly_like_lemons/everything.txt
i_rly_like_lemons/extras.py
i_rly_like_lemons/filter.txt
i_rly_like_lemons/get_words.py
i_rly_like_lemons/inverters.txt
i_rly_like_lemons/keywords.py
i_rly_like_lemons/negative.txt
i_rly_like_lemons/non_kwrds.txt
i_rly_like_lemons/positive.txt
i_rly_like_lemons/sentiment.py
i_rly_like_lemons-1.1.12.dist-info/LICENSE
i_rly_like_lemons-1.1.12.dist-info/METADATA
i_rly_like_lemons-1.1.12.dist-info/WHEEL
i_rly_like_lemons-1.1.12.dist-info/top_level.txt
i_rly_like_lemons-1.1.12.dist-info/RECORD
