Metadata-Version: 2.1
Name: i-rly-like-lemons
Version: 1.1.12
Summary: a hyper fast natural language proccesing module
Home-page: https://github.com/marmust/i-really-like-lemons
Author: 8AAFFF
Author-email: swingyy2@gmail.com
Classifier: Programming Language :: Python :: 3
Classifier: License :: OSI Approved :: MIT License
Classifier: Operating System :: OS Independent
Requires-Python: >=3.7
License-File: LICENSE
